lavlab/__init__.py
lavlab/omero_asyncio.py
lavlab/omero_util.py
lavlab/python_util.py
lavlab_python_utils-1.2.3.dist-info/METADATA
lavlab_python_utils-1.2.3.dist-info/WHEEL
lavlab_python_utils-1.2.3.dist-info/top_level.txt
lavlab_python_utils-1.2.3.dist-info/RECORD
