Metadata-Version: 2.1
Name: lavlab-python-utils
Version: 1.2.3
Summary: LaViolette Lab utility package
Author-email: Michael Barrett <mjbarrett@mcw.edu>
Project-URL: Homepage, https://github.com/laviolette-lab/lavlab-python-utils
Project-URL: Bug Tracker, https://github.com/laviolette-lab/lavlab-python-utils/issues
Classifier: Programming Language :: Python :: 3
Classifier: License :: OSI Approved :: MIT License
Classifier: Operating System :: OS Independent
Requires-Python: >=3.7
Requires-Dist: dask
Requires-Dist: omero-py (>=5.13.1)
Requires-Dist: tiatoolbox (>=1.4.0)
Provides-Extra: docs
Requires-Dist: sphinx (>=6.2.1) ; extra == 'docs'
Requires-Dist: docutils (>=0.18.1) ; extra == 'docs'
